{"is_source_file": true, "format": "JavaScript/JSX", "description": "This React component named SystemMetrics displays system status metrics in a UI card, including API latency, websocket connections, error rate, and active users.", "external_files": ["../../common"], "external_methods": [], "published": [], "classes": [], "methods": [{"name": "SystemMetrics()", "description": "A React functional component that renders system metrics within a styled card.", "scope": "", "scopeKind": ""}], "calls": ["React", "Card"], "search-terms": ["React", "SystemMetrics", "dashboard", "metrics", "status", "UI component"], "state": 2, "file_id": 57, "knowledge_revision": 141, "git_revision": "", "ctags": [{"_type": "tag", "name": "SystemMetrics", "path": "/home/kavia/workspace/code-generation/nutrition-connect-platform-173001-173010/nutrition_frontend/src/components/dashboard/widgets/SystemMetrics.jsx", "pattern": "/^export default function SystemMetrics() {$/", "language": "JavaScript", "kind": "function", "signature": "()"}], "hash": "9817b1b9ac0b7ed9be1e40a8ea86e009", "format-version": 4, "code-base-name": "nutrition_frontend", "filename": "nutrition_frontend/src/components/dashboard/widgets/SystemMetrics.jsx", "revision_history": [{"141": ""}]}